hpc_gateway/__init__.py
hpc_gateway/auth.py
hpc_gateway/config.py
hpc_gateway/factory.py
hpc_gateway/api/__init__.py
hpc_gateway/api/file.py
hpc_gateway/api/image.py
hpc_gateway/api/job.py
hpc_gateway/api/user.py
hpc_gateway/api/utils.py
hpc_gateway/model/__init__.py
hpc_gateway/model/database.py
hpc_gateway/model/f7t.py
hpc_gateway/model/job.py
hpc_gateway_sdk/__init__.py
hpc_gateway_sdk/version.py
marketplace_hpc-2.0.0.dist-info/LICENSE
marketplace_hpc-2.0.0.dist-info/METADATA
marketplace_hpc-2.0.0.dist-info/WHEEL
marketplace_hpc-2.0.0.dist-info/top_level.txt
marketplace_hpc-2.0.0.dist-info/RECORD
