Metadata-Version: 2.1
Name: marketplace-hpc
Version: 2.0.0
Summary: Materials MarketPlace HPC gateway app.
Home-page: https://github.com/materials-marketplace/hpc-gateway-app
Author: Jusong Yu
Author-email: jusong.yu@epfl.ch
License: MIT
Classifier: Development Status :: 2 - Pre-Alpha
Classifier: License :: OSI Approved :: MIT License
Classifier: Programming Language :: Python :: 3
Classifier: Programming Language :: Python :: 3 :: Only
Classifier: Programming Language :: Python :: 3.8
Classifier: Programming Language :: Python :: 3.9
Classifier: Programming Language :: Python :: 3.10
Classifier: Programming Language :: Python :: Implementation :: CPython
Requires-Python: >=3.8
License-File: LICENSE
Requires-Dist: marketplace-sdk (~=0.3.2)
Requires-Dist: requests (~=2.26.0)
Provides-Extra: deploy
Requires-Dist: Flask (~=2.0.1) ; extra == 'deploy'
Requires-Dist: Flask-PyMongo (~=2.3.0) ; extra == 'deploy'
Requires-Dist: pyfirecrest (~=1.2.0) ; extra == 'deploy'
Requires-Dist: python-dotenv (~=0.19) ; extra == 'deploy'
Provides-Extra: dev
Requires-Dist: bumpver (==2021.1114) ; extra == 'dev'
Requires-Dist: mongomock (~=4.1) ; extra == 'dev'
Requires-Dist: pre-commit (==2.15.0) ; extra == 'dev'
Requires-Dist: pytest (==6.2.5) ; extra == 'dev'
Requires-Dist: python-dotenv (==0.19.2) ; extra == 'dev'
Requires-Dist: requests-mock (~=1.10) ; extra == 'dev'
